rule_engine/__init__.py
rule_engine/error.py
rule_engine/operator.py
rule_engine/rule.py
tests/__init__.py
tests/test_operator.py
tests/test_rules.py
py_rule_engine-0.0.2.dist-info/METADATA
py_rule_engine-0.0.2.dist-info/WHEEL
py_rule_engine-0.0.2.dist-info/top_level.txt
py_rule_engine-0.0.2.dist-info/RECORD
